<?xml version='1.0' encoding='utf-8'?>
<root><theme>dark</theme><digital_cameras><quantity>2</quantity><camera_labels><label0>Camera 1</label0><label1>Camera 2</label1></camera_labels><camera_address><address0>0</address0><address1>1</address1></camera_address><default_feeds><defaultfeed0>0</defaultfeed0><defaultfeed1>0</defaultfeed1><defaultfeed2>0</defaultfeed2><defaultfeed3>0</defaultfeed3></default_feeds><resolution><feed0>4</feed0><feed1>4</feed1><feed2>4</feed2><feed3>4</feed3></resolution></digital_cameras><keybindings><switch_control_direction>UP</switch_control_direction><controller_sensitivity>None</controller_sensitivity><right_yaw>None</right_yaw><right_left>None</right_left><yaw_sensitivity>None</yaw_sensitivity><actuator5>None</actuator5><actuator6>None</actuator6><actuator7>None</actuator7><actuator8>None</actuator8></keybindings><sensors><quantity>3</quantity><viewType>0</viewType><sensor0><type>1</type></sensor0><sensor1><type>2</type></sensor1><sensor2><type>2</type></sensor2></sensors></root>